haystack_integrations/components/retrievers/py.typed
haystack_integrations/components/retrievers/singlestore_haystack/__init__.py
haystack_integrations/components/retrievers/singlestore_haystack/bm25_retriever.py
haystack_integrations/components/retrievers/singlestore_haystack/embedding_retriever.py
haystack_integrations/document_stores/py.typed
haystack_integrations/document_stores/singlestore_haystack/__about__.py
haystack_integrations/document_stores/singlestore_haystack/__init__.py
haystack_integrations/document_stores/singlestore_haystack/document_store.py
haystack_integrations/document_stores/singlestore_haystack/filter.py
singlestore_haystack-1.0.0.dist-info/METADATA
singlestore_haystack-1.0.0.dist-info/WHEEL
singlestore_haystack-1.0.0.dist-info/licenses/LICENSE
singlestore_haystack-1.0.0.dist-info/RECORD
