Metadata-Version: 2.4
Name: singlestore-haystack
Version: 1.0.0
Summary: Haystack 2.x Document Store for SingleStore
Project-URL: Documentation, https://github.com/singlestore-labs/singlestore-haystack#readme
Project-URL: Issues, https://github.com/singlestore-labs/singlestore-haystack/issues
Project-URL: Source, https://github.com/singlestore-labs/singlestore-haystack
Author-email: SingleStore <integration@singlestore.com>
License-Expression: Apache-2.0
License-File: LICENSE
Classifier: Development Status :: 4 - Beta
Classifier: License :: OSI Approved :: Apache Software License
Classifier: Programming Language :: Python
Classifier: Programming Language :: Python :: 3.9
Classifier: Programming Language :: Python :: 3.10
Classifier: Programming Language :: Python :: 3.11
Classifier: Programming Language :: Python :: 3.12
Classifier: Programming Language :: Python :: 3.13
Classifier: Programming Language :: Python :: Implementation :: CPython
Classifier: Programming Language :: Python :: Implementation :: PyPy
Requires-Python: >=3.9
Requires-Dist: haystack-ai>=2.11.0
Requires-Dist: singlestoredb>=1.16.6
Requires-Dist: typing-extensions
